{
	"$schema": "https://shadcn-svelte.com/schema/registry-item.json",
	"name": "mist-hero-two",
	"type": "registry:block",
	"description": "Mist-style two-column hero",
	"devDependencies": [
		"@lucide/svelte",
		"svelte"
	],
	"registryDependencies": [
		"button",
		"utils"
	],
	"files": [
		{
			"content": "<script lang=\"ts\">\n\timport { cn } from \"$UTILS$\";\n\timport Menu from \"@lucide/svelte/icons/menu\";\n\timport X from \"@lucide/svelte/icons/x\";\n\timport Button from \"$COMPONENTS$/ui/button/button.svelte\";\n\timport { scrollY } from \"svelte/reactivity/window\";\n\n\tlet menuItems = [\n\t\t{ name: \"Features\", href: \"#a\" },\n\t\t{ name: \"Solution\", href: \"#a\" },\n\t\t{ name: \"Pricing\", href: \"#a\" },\n\t\t{ name: \"About\", href: \"#a\" },\n\t];\n\tlet menuState = $state(false);\n\tlet isScrolled = $derived.by(() => {\n\t\tif (scrollY.current !== undefined && scrollY.current > 50) {\n\t\t\treturn true;\n\t\t}\n\t\treturn false;\n\t});\n</script>\n\n<header class=\"relative [--color-primary:theme(colors.indigo.500)]\">\n\t<nav\n\t\tdata-state={menuState && \"active\"}\n\t\tclass={cn(\n\t\t\t\"fixed z-20 w-full transition-all duration-300\",\n\t\t\tisScrolled && \"border-b border-black/5 bg-background/75 backdrop-blur-lg\"\n\t\t)}\n\t>\n\t\t<div class=\"mx-auto max-w-5xl px-6\">\n\t\t\t<div class=\"relative flex flex-wrap items-center justify-between gap-6 py-3 lg:gap-0\">\n\t\t\t\t<div class=\"flex w-full justify-between gap-6 lg:w-auto\">\n\t\t\t\t\t<a href=\"/\" aria-label=\"home\" class=\"flex items-center space-x-2\">\n\t\t\t\t\t\t<svg\n\t\t\t\t\t\t\txmlns=\"http://www.w3.org/2000/svg\"\n\t\t\t\t\t\t\twidth=\"22\"\n\t\t\t\t\t\t\theight=\"22\"\n\t\t\t\t\t\t\tviewBox=\"0 0 24 24\"\n\t\t\t\t\t\t\tfill=\"none\"\n\t\t\t\t\t\t\trole=\"img\"\n\t\t\t\t\t\t\tcolor=\"currentColor\"\n\t\t\t\t\t\t>\n\t\t\t\t\t\t\t<path\n\t\t\t\t\t\t\t\td=\"M22 18C22 19.4001 22 20.1002 21.7275 20.635C21.4878 21.1054 21.1054 21.4878 20.635 21.7275C20.1002 22 19.4001 22 18 22C16.5999 22 15.8998 22 15.365 21.7275C14.8946 21.4878 14.5122 21.1054 14.2725 20.635C14 20.1002 14 19.4001 14 18C14 16.5999 14 15.8998 14.2725 15.365C14.5122 14.8946 14.8946 14.5122 15.365 14.2725C15.8998 14 16.5999 14 18 14C19.4001 14 20.1002 14 20.635 14.2725C21.1054 14.5122 21.4878 14.8946 21.7275 15.365C22 15.8998 22 16.5999 22 18Z\"\n\t\t\t\t\t\t\t\tstroke=\"currentColor\"\n\t\t\t\t\t\t\t\tstroke-width=\"1.5\"\n\t\t\t\t\t\t\t></path>\n\t\t\t\t\t\t\t<path\n\t\t\t\t\t\t\t\td=\"M22 10C22 11.4001 22 12.1002 21.7275 12.635C21.4878 13.1054 21.1054 13.4878 20.635 13.7275C20.1002 14 19.4001 14 18 14C16.5999 14 15.8998 14 15.365 13.7275C14.8946 13.4878 14.5122 13.1054 14.2725 12.635C14 12.1002 14 11.4001 14 10C14 8.59987 14 7.8998 14.2725 7.36502C14.5122 6.89462 14.8946 6.51217 15.365 6.27248C15.8998 6 16.5999 6 18 6C19.4001 6 20.1002 6 20.635 6.27248C21.1054 6.51217 21.4878 6.89462 21.7275 7.36502C22 7.8998 22 8.59987 22 10Z\"\n\t\t\t\t\t\t\t\tstroke=\"currentColor\"\n\t\t\t\t\t\t\t\tstroke-width=\"1.5\"\n\t\t\t\t\t\t\t></path>\n\t\t\t\t\t\t\t<path\n\t\t\t\t\t\t\t\td=\"M14 18C14 19.4001 14 20.1002 13.7275 20.635C13.4878 21.1054 13.1054 21.4878 12.635 21.7275C12.1002 22 11.4001 22 10 22C8.59987 22 7.8998 22 7.36502 21.7275C6.89462 21.4878 6.51217 21.1054 6.27248 20.635C6 20.1002 6 19.4001 6 18C6 16.5999 6 15.8998 6.27248 15.365C6.51217 14.8946 6.89462 14.5122 7.36502 14.2725C7.8998 14 8.59987 14 10 14C11.4001 14 12.1002 14 12.635 14.2725C13.1054 14.5122 13.4878 14.8946 13.7275 15.365C14 15.8998 14 16.5999 14 18Z\"\n\t\t\t\t\t\t\t\tstroke=\"currentColor\"\n\t\t\t\t\t\t\t\tstroke-width=\"1.5\"\n\t\t\t\t\t\t\t></path>\n\t\t\t\t\t\t\t<path\n\t\t\t\t\t\t\t\topacity=\"0.4\"\n\t\t\t\t\t\t\t\td=\"M10 6C10 7.40013 10 8.1002 9.72752 8.63497C9.48783 9.10538 9.10538 9.48783 8.63498 9.72752C8.1002 10 7.40013 10 6 10C4.59987 10 3.8998 10 3.36502 9.72751C2.89462 9.48783 2.51217 9.10538 2.27248 8.63497C2 8.10019 2 7.40013 2 6C2 4.59987 2 3.8998 2.27248 3.36502C2.51217 2.89462 2.89462 2.51217 3.36502 2.27248C3.8998 2 4.59987 2 6 2C7.40013 2 8.1002 2 8.63498 2.27248C9.10538 2.51217 9.48783 2.89462 9.72752 3.36502C10 3.8998 10 4.59987 10 6Z\"\n\t\t\t\t\t\t\t\tstroke=\"currentColor\"\n\t\t\t\t\t\t\t\tstroke-width=\"1.5\"\n\t\t\t\t\t\t\t></path>\n\t\t\t\t\t\t</svg>\n\t\t\t\t\t</a>\n\n\t\t\t\t\t<button\n\t\t\t\t\t\tonclick={() => (menuState = !menuState)}\n\t\t\t\t\t\taria-label={menuState == true ? \"Close Menu\" : \"Open Menu\"}\n\t\t\t\t\t\tclass=\"relative z-20 -m-2.5 -mr-4 block cursor-pointer p-2.5 lg:hidden\"\n\t\t\t\t\t>\n\t\t\t\t\t\t<Menu\n\t\t\t\t\t\t\tclass=\"m-auto size-6 duration-200 in-data-[state=active]:scale-0 in-data-[state=active]:rotate-180 in-data-[state=active]:opacity-0\"\n\t\t\t\t\t\t/>\n\t\t\t\t\t\t<X\n\t\t\t\t\t\t\tclass=\"absolute inset-0 m-auto size-6 scale-0 -rotate-180 opacity-0 duration-200 in-data-[state=active]:scale-100 in-data-[state=active]:rotate-0 in-data-[state=active]:opacity-100\"\n\t\t\t\t\t\t/>\n\t\t\t\t\t</button>\n\n\t\t\t\t\t<div class=\"m-auto hidden size-fit lg:block\">\n\t\t\t\t\t\t<ul class=\"flex gap-1\">\n\t\t\t\t\t\t\t{#each menuItems as item, index}\n\t\t\t\t\t\t\t\t<li>\n\t\t\t\t\t\t\t\t\t<Button variant=\"ghost\" size=\"sm\">\n\t\t\t\t\t\t\t\t\t\t<a href={item.href} class=\"text-base\">\n\t\t\t\t\t\t\t\t\t\t\t<span>{item.name}</span>\n\t\t\t\t\t\t\t\t\t\t</a>\n\t\t\t\t\t\t\t\t\t</Button>\n\t\t\t\t\t\t\t\t</li>\n\t\t\t\t\t\t\t{/each}\n\t\t\t\t\t\t</ul>\n\t\t\t\t\t</div>\n\t\t\t\t</div>\n\n\t\t\t\t<div\n\t\t\t\t\tclass=\"mb-6 hidden w-full flex-wrap items-center justify-end space-y-8 rounded-3xl border bg-background p-6 shadow-2xl shadow-zinc-300/20 in-data-[state=active]:block md:flex-nowrap lg:m-0 lg:flex lg:w-fit lg:gap-6 lg:space-y-0 lg:border-transparent lg:bg-transparent lg:p-0 lg:shadow-none lg:in-data-[state=active]:flex dark:shadow-none dark:lg:bg-transparent\"\n\t\t\t\t>\n\t\t\t\t\t<div class=\"lg:hidden\">\n\t\t\t\t\t\t<ul class=\"space-y-6 text-base\">\n\t\t\t\t\t\t\t{#each menuItems as item, index}\n\t\t\t\t\t\t\t\t<li>\n\t\t\t\t\t\t\t\t\t<a\n\t\t\t\t\t\t\t\t\t\thref={item.href}\n\t\t\t\t\t\t\t\t\t\tclass=\"block text-muted-foreground duration-150 hover:text-accent-foreground\"\n\t\t\t\t\t\t\t\t\t>\n\t\t\t\t\t\t\t\t\t\t<span>{item.name}</span>\n\t\t\t\t\t\t\t\t\t</a>\n\t\t\t\t\t\t\t\t</li>\n\t\t\t\t\t\t\t{/each}\n\t\t\t\t\t\t</ul>\n\t\t\t\t\t</div>\n\t\t\t\t\t<div\n\t\t\t\t\t\tclass=\"flex w-full flex-col space-y-3 sm:flex-row sm:gap-3 sm:space-y-0 md:w-fit\"\n\t\t\t\t\t>\n\t\t\t\t\t\t<Button\n\t\t\t\t\t\t\tvariant=\"ghost\"\n\t\t\t\t\t\t\tsize=\"sm\"\n\t\t\t\t\t\t\tclass={cn(isScrolled && \"lg:hidden\", \"rounded-full\")}\n\t\t\t\t\t\t\thref=\"#\"\n\t\t\t\t\t\t>\n\t\t\t\t\t\t\tLogin\n\t\t\t\t\t\t</Button>\n\t\t\t\t\t\t<Button\n\t\t\t\t\t\t\thref=\"#\"\n\t\t\t\t\t\t\tsize=\"sm\"\n\t\t\t\t\t\t\tvariant=\"mdefault\"\n\t\t\t\t\t\t\tclass={cn(isScrolled && \"lg:hidden\", \"rounded-full\")}\n\t\t\t\t\t\t>\n\t\t\t\t\t\t\tSign Up\n\t\t\t\t\t\t</Button>\n\t\t\t\t\t\t<Button\n\t\t\t\t\t\t\tsize=\"sm\"\n\t\t\t\t\t\t\tclass={cn(isScrolled ? \"lg:inline-flex\" : \"hidden\")}\n\t\t\t\t\t\t\thref=\"#\"\n\t\t\t\t\t\t>\n\t\t\t\t\t\t\t<span>Get Started</span>\n\t\t\t\t\t\t</Button>\n\t\t\t\t\t</div>\n\t\t\t\t</div>\n\t\t\t</div>\n\t\t</div>\n\t</nav>\n</header>\n",
			"type": "registry:component",
			"target": "mist/mhero/two/header.svelte"
		},
		{
			"content": "<script lang=\"ts\">\n\timport Button from \"$COMPONENTS$/ui/button/button.svelte\";\n\timport Sparkle from \"@lucide/svelte/icons/sparkle\";\n\timport Header from \"./header.svelte\";\n</script>\n\n<div class=\"relative\">\n\t<Header />\n\t<main class=\"[--color-primary:var(--color-indigo-500)]\">\n\t\t<section\n\t\t\tclass=\"relative overflow-hidden border-e-foreground before:absolute before:inset-1 before:h-[calc(100%-8rem)] before:rounded-2xl before:bg-muted sm:before:inset-2 md:before:rounded-[2rem] lg:before:h-[calc(100%-14rem)]\"\n\t\t>\n\t\t\t<div class=\"py-20 md:py-36\">\n\t\t\t\t<div class=\"relative z-10 mx-auto max-w-5xl px-6 text-center\">\n\t\t\t\t\t<div>\n\t\t\t\t\t\t<a\n\t\t\t\t\t\t\thref=\"#\"\n\t\t\t\t\t\t\tclass=\"mx-auto flex w-fit items-center justify-center gap-2 rounded-md py-0.5 pr-3 pl-1 transition-colors duration-150 hover:bg-foreground/5\"\n\t\t\t\t\t\t>\n\t\t\t\t\t\t\t<div\n\t\t\t\t\t\t\t\taria-hidden=\"true\"\n\t\t\t\t\t\t\t\tclass=\"relative flex size-5 items-center justify-center rounded border border-background bg-linear-to-b from-primary to-foreground shadow-md ring-1 shadow-black/20 ring-black/10 dark:inset-shadow-2xs\"\n\t\t\t\t\t\t\t>\n\t\t\t\t\t\t\t\t<div\n\t\t\t\t\t\t\t\t\tclass=\"absolute inset-x-0 inset-y-1.5 border-y border-dotted border-white/25\"\n\t\t\t\t\t\t\t\t></div>\n\t\t\t\t\t\t\t\t<div\n\t\t\t\t\t\t\t\t\tclass=\"absolute inset-x-1.5 inset-y-0 border-x border-dotted border-white/25\"\n\t\t\t\t\t\t\t\t></div>\n\t\t\t\t\t\t\t\t<Sparkle class=\"size-3 fill-white stroke-white drop-shadow\" />\n\t\t\t\t\t\t\t</div>\n\t\t\t\t\t\t\t<span class=\"font-medium\">Introducing Mist Agents</span>\n\t\t\t\t\t\t</a>\n\t\t\t\t\t\t<h1\n\t\t\t\t\t\t\tclass=\"mx-auto mt-8 max-w-3xl text-4xl font-bold tracking-tight text-balance sm:text-5xl\"\n\t\t\t\t\t\t>\n\t\t\t\t\t\t\tBuild 10x Faster with Mist\n\t\t\t\t\t\t</h1>\n\t\t\t\t\t\t<p class=\"mx-auto my-6 max-w-xl text-xl text-balance text-muted-foreground\">\n\t\t\t\t\t\t\tCraft. Build. Ship Modern Websites With AI Support.\n\t\t\t\t\t\t</p>\n\n\t\t\t\t\t\t<div class=\"flex items-center justify-center gap-3\">\n\t\t\t\t\t\t\t<Button variant=\"mdefault\" size=\"lg\">\n\t\t\t\t\t\t\t\t<span class=\"text-nowrap\">Start Building</span>\n\t\t\t\t\t\t\t</Button>\n\t\t\t\t\t\t\t<Button size=\"lg\" variant=\"outline\">\n\t\t\t\t\t\t\t\t<span class=\"text-nowrap\">Watch Video</span>\n\t\t\t\t\t\t\t</Button>\n\t\t\t\t\t\t</div>\n\t\t\t\t\t</div>\n\t\t\t\t</div>\n\t\t\t\t<div class=\"relative\">\n\t\t\t\t\t<div class=\"relative z-10 mx-auto max-w-5xl px-6\">\n\t\t\t\t\t\t<div class=\"mt-12 md:mt-16\">\n\t\t\t\t\t\t\t<div\n\t\t\t\t\t\t\t\tclass=\"relative mx-auto overflow-hidden rounded-(--radius) border border-transparent bg-background shadow-lg ring-1 shadow-black/10 ring-black/10\"\n\t\t\t\t\t\t\t>\n\t\t\t\t\t\t\t\t<img\n\t\t\t\t\t\t\t\t\tsrc=\"/mist/tailark-2.png\"\n\t\t\t\t\t\t\t\t\talt=\"app screen\"\n\t\t\t\t\t\t\t\t\twidth=\"2880\"\n\t\t\t\t\t\t\t\t\theight=\"1842\"\n\t\t\t\t\t\t\t\t/>\n\t\t\t\t\t\t\t</div>\n\t\t\t\t\t\t</div>\n\t\t\t\t\t</div>\n\t\t\t\t</div>\n\t\t\t</div>\n\t\t</section>\n\t</main>\n</div>\n",
			"type": "registry:component",
			"target": "mist/mhero/two/hero-two.svelte"
		}
	]
}